dmx/compressor/__init__.py
dmx/compressor/advanced_recipe.py
dmx/compressor/functional/__init__.py
dmx/compressor/functional/approximate.py
dmx/compressor/functional/functions.py
dmx/compressor/fx/__init__.py
dmx/compressor/fx/tracer.py
dmx/compressor/fx/transform.py
dmx/compressor/fx/transformer/__init__.py
dmx/compressor/fx/transformer/configuration_transformer.py
dmx/compressor/fx/transformer/custom_ops.py
dmx/compressor/fx/transformer/dmx_aware_transformer.py
dmx/compressor/fx/transformer/export_transformer.py
dmx/compressor/fx/transformer/input_output_transformer.py
dmx/compressor/fx/transformer/nodedict_transformer.py
dmx/compressor/fx/transformer/qdq_transformer.py
dmx/compressor/fx/transformer/record_input_interpreter.py
dmx/compressor/fx/transformer/utils.py
dmx/compressor/layer_reconstruction.py
dmx/compressor/modeling/__init__.py
dmx/compressor/modeling/hf.py
dmx/compressor/modeling/model.py
dmx/compressor/modeling/nn/__init__.py
dmx/compressor/modeling/nn/core.py
dmx/compressor/modeling/nn/custom_modules.py
dmx/compressor/modeling/nn/experimental.py
dmx/compressor/modeling/nn/torch_modules.py
dmx/compressor/numerical/__init__.py
dmx/compressor/numerical/cast.py
dmx/compressor/numerical/custom_lib.py
dmx/compressor/numerical/format.py
dmx/compressor/numerical/observer.py
dmx/compressor/numerical/onnx.py
dmx/compressor/numerical/smoothquant.py
dmx/compressor/perf_proxy.py
dmx/compressor/plugins.py
dmx/compressor/quant/README.md
dmx/compressor/quant/__init__.py
dmx/compressor/quant/quant_cpu/bit_helper.cpp
dmx/compressor/quant/quant_cpu/quant_cpu.cpp
dmx/compressor/quant/quant_cpu/quant_cpu.h
dmx/compressor/quant/quant_cpu/sim_helper.cpp
dmx/compressor/quant/quant_cuda/bit_helper.cu
dmx/compressor/quant/quant_cuda/block_kernel.cu
dmx/compressor/quant/quant_cuda/fixed_point_kernel.cu
dmx/compressor/quant/quant_cuda/float_kernel.cu
dmx/compressor/quant/quant_cuda/quant.cu
dmx/compressor/quant/quant_cuda/quant_cuda.cpp
dmx_compressor-0.1.11.dist-info/LICENSE
dmx_compressor-0.1.11.dist-info/METADATA
dmx_compressor-0.1.11.dist-info/NOTICE
dmx_compressor-0.1.11.dist-info/WHEEL
dmx_compressor-0.1.11.dist-info/RECORD
