Metadata-Version: 2.3
Name: dmx-compressor
Version: 0.1.11
Summary: d-Matrix Compressor
Author: Tristan Webb
Author-email: twebb@d-matrix.ai
Requires-Python: >=3.9
Classifier: Programming Language :: Python :: 3
Classifier: Programming Language :: Python :: 3.9
Classifier: Programming Language :: Python :: 3.10
Classifier: Programming Language :: Python :: 3.11
Classifier: Programming Language :: Python :: 3.12
Classifier: Programming Language :: Python :: 3.13
Requires-Dist: accelerate (>=1.5,<2.0)
Requires-Dist: bidict (>=0.22,<1.0)
Requires-Dist: datasets (>=2.0)
Requires-Dist: diffusers (>0.25,<1.0)
Requires-Dist: evaluate (>=0.4.1,<0.5)
Requires-Dist: graphviz (>=0.21,<0.22)
Requires-Dist: numpy (>1.0)
Requires-Dist: parse (>=1.19,<2.0)
Requires-Dist: pptree (>=3.1,<4.0)
Requires-Dist: pytest (>=8.0,<9.0)
Requires-Dist: scikit-optimize (==0.10.2)
Requires-Dist: tabulate (>=0.9.0,<0.10.0)
Requires-Dist: torch (>=2.7,<3.0)
Requires-Dist: torchvision (>=0.22,<1.0)
Requires-Dist: tqdm (>=4.0,<5.0)
Requires-Dist: transformers (>=4.35.0,<4.50.0)
